oisp/__init__.py
oisp/account.py
oisp/client.py
oisp/data_query.py
oisp/device.py
oisp/oisp_token.py
oisp/oisp_user.py
oisp/utils.py
oisp-0.2.1.dist-info/LICENSE
oisp-0.2.1.dist-info/METADATA
oisp-0.2.1.dist-info/WHEEL
oisp-0.2.1.dist-info/top_level.txt
oisp-0.2.1.dist-info/RECORD
